{
  "recentFiles": [
    {
      "basename": "笔记",
      "path": "docs/课程/金融工程学/笔记.md"
    },
    {
      "basename": "金融工程课件（4）",
      "path": "pdf/金融工程/金融工程课件（4）.pdf"
    },
    {
      "basename": "金融工程课件（6）",
      "path": "pdf/金融工程/金融工程课件（6）.pdf"
    },
    {
      "basename": "金融工程课件（7）",
      "path": "pdf/金融工程/金融工程课件（7）.pdf"
    },
    {
      "basename": "作业",
      "path": "docs/课程/金融工程学/作业.md"
    },
    {
      "basename": "金融工程课件（5）",
      "path": "pdf/金融工程/金融工程课件（5）.pdf"
    },
    {
      "basename": "金融工程课件（3）",
      "path": "pdf/金融工程/金融工程课件（3）.pdf"
    },
    {
      "basename": "金融工程课件（2）",
      "path": "pdf/金融工程/金融工程课件（2）.pdf"
    },
    {
      "basename": "金融工程课件（1）",
      "path": "pdf/金融工程/金融工程课件（1）.pdf"
    },
    {
      "basename": "郑振龙《金融工程》（第5版）笔记和课后习题（含考研真题）详解答案",
      "path": "docs/课程/金融工程学/郑振龙《金融工程》（第5版）笔记和课后习题（含考研真题）详解答案.pdf"
    },
    {
      "basename": "金融工程导学课程",
      "path": "pdf/金融工程/金融工程导学课程.pdf"
    },
    {
      "basename": "可扩展",
      "path": "docs/课程/软件体系结构/笔记/可扩展.md"
    },
    {
      "basename": "SpringMVC",
      "path": "docs/课程/软件体系结构/笔记/SSM/SpringMVC.md"
    },
    {
      "basename": "p13",
      "path": "docs/课程/编译原理/作业/p13.md"
    },
    {
      "basename": "机器无关优化",
      "path": "docs/课程/编译原理/笔记/机器无关优化.md"
    },
    {
      "basename": "SpringBoot",
      "path": "docs/课程/软件体系结构/笔记/SpringBoot.md"
    },
    {
      "basename": "数据迁移更换硬盘",
      "path": "docs/pc日常/数据备份/数据迁移更换硬盘.md"
    },
    {
      "basename": "数据备份",
      "path": "docs/pc日常/数据备份/数据备份.md"
    },
    {
      "basename": "2.3",
      "path": "docs/课程/编译原理/作业/答案/dragon-book-exercise-answers-master/ch02/2.3/2.3.md"
    },
    {
      "basename": "2.4",
      "path": "docs/课程/编译原理/作业/答案/dragon-book-exercise-answers-master/ch02/2.4/2.4.md"
    },
    {
      "basename": "编译原理",
      "path": "docs/课程/编译原理/编译原理.md"
    },
    {
      "basename": "2.2.3-4",
      "path": "docs/课程/编译原理/作业/答案/dragon-book-exercise-answers-master/ch02/2.2/assets/2.2.3-4.png"
    },
    {
      "basename": "hello",
      "path": "docs/课程/操作系统/代码/os-model/hello.py"
    },
    {
      "basename": "腾讯天美游戏端开发",
      "path": "_private_/个人相关/腾讯天美游戏端开发.md"
    },
    {
      "basename": "temp",
      "path": "_private_/临时/temp.md"
    },
    {
      "basename": "抽象ADT",
      "path": "docs/软件工程/编程思想与规范/抽象ADT.md"
    },
    {
      "basename": "Collections工具类",
      "path": "docs/java/java基础/Util/集合/Collections工具类.md"
    },
    {
      "basename": "Math类",
      "path": "docs/java/java基础/Util/Math类.md"
    },
    {
      "basename": "thread-sync",
      "path": "docs/课程/操作系统/代码/thread-lib/thread-sync.h"
    },
    {
      "basename": "hello",
      "path": "docs/课程/操作系统/代码/thread-lib/hello.c"
    },
    {
      "basename": "fish",
      "path": "docs/课程/操作系统/代码/fish/fish.c"
    },
    {
      "basename": "数学",
      "path": "docs/算法/数学.md"
    },
    {
      "basename": "线性代数engin",
      "path": "docs/c++/库/线性代数engin.md"
    },
    {
      "basename": "2",
      "path": "docs/c++/笔记（整理前）/2.md"
    },
    {
      "basename": "金融大数据p4",
      "path": "Slide/金融大数据p4.md"
    },
    {
      "basename": "金融大数据p2",
      "path": "Slide/金融大数据p2.md"
    },
    {
      "basename": "index",
      "path": "docs/index.md"
    },
    {
      "basename": "Chapter_9",
      "path": "docs/课程/编译原理/课件/Chapter_9.pdf"
    },
    {
      "basename": "12.3",
      "path": "docs/课程/编译原理/作业/答案/dragon-book-exercise-answers-master/ch12/12.3/12.3.md"
    },
    {
      "basename": "12.7",
      "path": "docs/课程/编译原理/作业/答案/dragon-book-exercise-answers-master/ch12/12.7/12.7.md"
    },
    {
      "basename": "8.2",
      "path": "docs/课程/编译原理/作业/答案/dragon-book-exercise-answers-master/ch08/8.2/8.2.md"
    },
    {
      "basename": "p12",
      "path": "docs/课程/编译原理/作业/p12.md"
    },
    {
      "basename": "笔记",
      "path": "docs/保研/机试/笔记.md"
    },
    {
      "basename": "使用 VSCode 编写 C++ 单文件程序 (Windows 系统)_md · main · 田 昊东 _ NJUCS-BAOYAN · GitLab",
      "path": "docs/保研/机试/使用 VSCode 编写 C++ 单文件程序 (Windows 系统)_md · main · 田 昊东 _ NJUCS-BAOYAN · GitLab.md"
    },
    {
      "basename": "数组与字符串",
      "path": "docs/算法/数组与字符串.md"
    },
    {
      "basename": "P5410 【模板】扩展 KMP_exKMP（Z 函数） - 洛谷 _ 计算机科学教育新生态",
      "path": "docs/Blog/P5410 【模板】扩展 KMP_exKMP（Z 函数） - 洛谷 _ 计算机科学教育新生态.md"
    },
    {
      "basename": "中间代码生成",
      "path": "docs/课程/编译原理/笔记/中间代码生成.md"
    },
    {
      "basename": "离散数学",
      "path": "docs/保研/数学/离散数学.md"
    },
    {
      "basename": "【英语】问题准备",
      "path": "docs/保研/面试/英语/【英语】问题准备.md"
    },
    {
      "basename": "问题",
      "path": "docs/保研/面试/问题.md"
    }
  ],
  "omittedPaths": [],
  "maxLength": null,
  "openType": "tab"
}